cuecmd/__init__.py
cuecmd/__main__.py
cuecmd/execute_commands.py
cuecmd/main.py
opencue_cuecmd-1.13.8.dist-info/METADATA
opencue_cuecmd-1.13.8.dist-info/WHEEL
opencue_cuecmd-1.13.8.dist-info/entry_points.txt
opencue_cuecmd-1.13.8.dist-info/RECORD
