Metadata-Version: 2.1
Name: opencue_cuecmd
Version: 1.13.8
Summary: Cuecmd is a command-line tool for OpenCue that executes a list of commands as frames on the render farm. It enables batch processing by chunking commands and submitting them as OpenCue jobs.
Requires-Python: >3.7
Requires-Dist: opencue-pycue
Requires-Dist: opencue-pyoutline
Provides-Extra: dev
Requires-Dist: black; extra == 'dev'
Requires-Dist: isort; extra == 'dev'
Requires-Dist: mock==2.0.0; extra == 'dev'
Requires-Dist: pyfakefs==5.2.3; extra == 'dev'
Requires-Dist: pylint; extra == 'dev'
Requires-Dist: pytest; extra == 'dev'
Requires-Dist: pytest-cov; extra == 'dev'
Requires-Dist: pytest-mock; extra == 'dev'
Provides-Extra: test
Requires-Dist: mock==2.0.0; extra == 'test'
Requires-Dist: pyfakefs==5.2.3; extra == 'test'
Requires-Dist: pytest; extra == 'test'
Requires-Dist: pytest-cov; extra == 'test'
Requires-Dist: pytest-mock; extra == 'test'
